[
  {
    "file": "110kV-Transformer-Bushing-in-Operation-at-Yunnan-Huayou-Youtian-Project.html",
    "title": "110kV Transformer Bushing in Operation at Yunnan Huayou Youtian Project",
    "customer": "TBEA Xinjiang Transformer Co",
    "project": "Shandong Qixing High Voltage Electric Co",
    "products": " RIP/RIF Oil-Air Transformer Bushing RIP/RIF Oil-SF6 Transformer Bushing RIP/RIF Oil-Oil Transformer Bushing RIP/RIF High Current Transformer Bushing RIP/RIF GIS Outlet Bushing RIP/RIF Wall Bushing F",
    "operationTime": "at Yunnan Huayou Youtian Project-Shandong Qixing High Voltage Electric Co",
    "description": ", Ltd Project: Yunnan Huayou Youtian Project Products: 110kV Transformer Bushing Operation time: 18th Sep.",
    "images": [
      "1731894078716949488901574656",
      "1731894930716953063098699776",
      "1768468846870355185425739776",
      "1768524315870587839131742208",
      "1768543449870668094219554816",
      "1768811237871791276305608704",
      "1769394598874238072085098496"
    ]
  },
  {
    "file": "126kV-GIS-Bushing-in-Operation-at-Ningxia-Dadi-Tire-Project.html",
    "title": "126kV GIS Bushing in Operation at Ningxia Dadi Tire Project",
    "customer": "Pinggao Group Weihai High Voltage Apparatus Co",
    "project": "Shandong Qixing High Voltage Electric Co",
    "products": " RIP/RIF Oil-Air Transformer Bushing RIP/RIF Oil-SF6 Transformer Bushing RIP/RIF Oil-Oil Transformer Bushing RIP/RIF High Current Transformer Bushing RIP/RIF GIS Outlet Bushing RIP/RIF Wall Bushing F",
    "operationTime": "at Ningxia Dadi Tire Project-Shandong Qixing High Voltage Electric Co",
    "description": "2015 Previous: 330kV Transformer Bushing in Operation at the Energy Storage Power Station of the Gansu Longyuan Linze Banqiao Beitan 500MW Photovoltaic Desert Control Project.",
    "images": [
      "1731894078716949488901574656",
      "1731894930716953063098699776",
      "1768468846870355185425739776",
      "1768524315870587839131742208",
      "1768534400870630139228614656",
      "1768534401870630141296418816",
      "1768534401870630143154495488",
      "1768534402870630145008377856",
      "1768534402870630146883231744",
      "1768811237871791276305608704",
      "1769394598874238072085098496"
    ]
  },
  {
    "file": "126kV-Oil-SF6-Bushing-in-Operation-at-Jiangxi-Jiepai-Hydropower-Station.html",
    "title": "126kV Oil-SF6 Bushing in Operation at Jiangxi Jiepai Hydropower Station",
    "customer": "Jiangsu Yawei Transformer Co",
    "project": "Jiangxi Jiepai Hydropower Station Products: 126kV Oil-SF6 Bushing Operation time: 13th Apr",
    "products": " RIP/RIF Oil-Air Transformer Bushing RIP/RIF Oil-SF6 Transformer Bushing RIP/RIF Oil-Oil Transformer Bushing RIP/RIF High Current Transformer Bushing RIP/RIF GIS Outlet Bushing RIP/RIF Wall Bushing F",
    "operationTime": "at Jiangxi Jiepai Hydropower Station-Shandong Qixing High Voltage Electric Co",
    "description": ", Ltd Project: Jiangxi Jiepai Hydropower Station Products: 126kV Oil-SF6 Bushing Operation time: 13th Apr.",
    "images": [
      "1731894078716949488901574656",
      "1731894930716953063098699776",
      "1768468846870355185425739776",
      "1768524315870587839131742208",
      "1768541581870660256348835840",
      "1768541581870660258190094336",
      "1768541582870660260274663424",
      "1768541582870660262917074944",
      "1768811237871791276305608704",
      "1769394598874238072085098496"
    ]
  },
  {
    "file": "126kV-Transformer-Bushing-in-Operation-at-Hejing-Yixin-Photovoltaic-Grid-Connected-Power-Station.html",
    "title": "126kV Transformer Bushing in Operation at Hejing Yixin Photovoltaic Grid-Connected Power Station",
    "customer": "TBEA Xinjiang Transformer Group Co",
    "project": "Hejing Yixin Photovoltaic Grid-Connected Power Station Products: 126kV Transformer Bushing Operation time: 7th Jan",
    "products": " RIP/RIF Oil-Air Transformer Bushing RIP/RIF Oil-SF6 Transformer Bushing RIP/RIF Oil-Oil Transformer Bushing RIP/RIF High Current Transformer Bushing RIP/RIF GIS Outlet Bushing RIP/RIF Wall Bushing F",
    "operationTime": "at Hejing Yixin Photovoltaic Grid-Connected Power Station-Shandong Qixing High Voltage Electric Co",
    "description": "2016 Previous: 252kV Transformer Bushing in Operation at Hebei Project Next: 330kV Transformer Bushing in Operation at the Energy Storage Power Station of the Gansu Longyuan Linze Banqiao Beitan 500MW Photovoltaic Desert Control Project.",
    "images": [
      "1731894078716949488901574656",
      "1731894930716953063098699776",
      "1768468846870355185425739776",
      "1768524315870587839131742208",
      "1768534060870628710564790272",
      "1768534060870628712527732736",
      "1768534060870628714310311936",
      "1768534061870628716185165824",
      "1768811237871791276305608704",
      "1769394598874238072085098496"
    ]
  },
  {
    "file": "126kV-Transformer-Bushing-in-Operation-at-Xinjiang-Project.html",
    "title": "126kV Transformer Bushing in Operation at Xinjiang Project",
    "customer": "TBEA Xinjiang Transformer Group Co",
    "project": "Shandong Qixing High Voltage Electric Co",
    "products": " RIP/RIF Oil-Air Transformer Bushing RIP/RIF Oil-SF6 Transformer Bushing RIP/RIF Oil-Oil Transformer Bushing RIP/RIF High Current Transformer Bushing RIP/RIF GIS Outlet Bushing RIP/RIF Wall Bushing F",
    "operationTime": "at Xinjiang Project-Shandong Qixing High Voltage Electric Co",
    "description": "2016 Previous: 126kV Oil-SF6 Bushing in Operation at Jiangxi Jiepai Hydropower Station Next: 252kV Transformer Bushing in Operation on the Chengdu-Chongqing High-Speed Railway Let Us know Your Request  Shandong Qixing High Voltage Electric Co.",
    "images": [
      "1731894078716949488901574656",
      "1731894930716953063098699776",
      "1768468846870355185425739776",
      "1768524315870587839131742208",
      "1768541773870661064624771072",
      "1768541774870661066487001088",
      "1768541774870661068080836608",
      "1768541775870661069683060736",
      "1768541775870661071331422208",
      "1768541775870661072946229248",
      "1768811237871791276305608704",
      "1769394598874238072085098496"
    ]
  },
  {
    "file": "220kV-Bushing-in-Operation-on-the-Lhasa-Nyingchi-Railway.html",
    "title": "220kV Bushing in Operation on the Lhasa-Nyingchi Railway",
    "customer": "Yunnan Transformer Electrical Co",
    "project": "Lhasa-Nyingchi Railway Products: 220kV Transformer Bushing Operation time: 9th Feb",
    "products": " RIP/RIF Oil-Air Transformer Bushing RIP/RIF Oil-SF6 Transformer Bushing RIP/RIF Oil-Oil Transformer Bushing RIP/RIF High Current Transformer Bushing RIP/RIF GIS Outlet Bushing RIP/RIF Wall Bushing F",
    "operationTime": "on the Lhasa-Nyingchi Railway-Shandong Qixing High Voltage Electric Co",
    "description": "2020 Previous: World's First 550 kV Rectifier Transformer Powered by Qixing Bushings Next: 252kV Transformer Bushing in Operation at Sichuan Batang Substation (China State Grid Project) Let Us know Your Request  Shandong Qixing High Voltage Electric Co.",
    "images": [
      "1731894078716949488901574656",
      "1731894930716953063098699776",
      "1768468846870355185425739776",
      "1768524315870587839131742208",
      "1768533551870626578537148416",
      "1768533552870626581506715648",
      "1768533553870626584526614528",
      "1768533553870626587177414656",
      "1768811237871791276305608704",
      "1769394598874238072085098496"
    ]
  },
  {
    "file": "220kV-Transformer-Bushing-in-Operation-at-Wuhai-Power-Supply-Bureau-s-220-Baoshan-Substation.html",
    "title": "220kV Transformer Bushing in Operation at Wuhai Power Supply Bureau's 220 Baoshan Substation",
    "customer": "Hebei Jingdian Electric Power Construction CO",
    "project": "Wuhai Power Supply Bureau's 220 Baoshan Substation Products: 220kV Transformer Bushing Operation time: 3rd Apr",
    "products": " RIP/RIF Oil-Air Transformer Bushing RIP/RIF Oil-SF6 Transformer Bushing RIP/RIF Oil-Oil Transformer Bushing RIP/RIF High Current Transformer Bushing RIP/RIF GIS Outlet Bushing RIP/RIF Wall Bushing F",
    "operationTime": "at Wuhai Power Supply Bureau's 220 Baoshan Substation-Shandong Qixing High Voltage Electric Co",
    "description": ", Ltd Project: Wuhai Power Supply Bureau's 220 Baoshan Substation Products: 220kV Transformer Bushing Operation time: 3rd Apr.",
    "images": [
      "1731894078716949488901574656",
      "1731894930716953063098699776",
      "1768468846870355185425739776",
      "1768524315870587839131742208",
      "1768542055870662246827102208",
      "1768811237871791276305608704",
      "1769394598874238072085098496"
    ]
  },
  {
    "file": "252kV-Transformer-Bushing-in-Operation-at-Hebei-Project.html",
    "title": "252kV Transformer Bushing in Operation at Hebei Project",
    "customer": "Baoding Tianwei Baobian Electric Co",
    "project": "Shandong Qixing High Voltage Electric Co",
    "products": " RIP/RIF Oil-Air Transformer Bushing RIP/RIF Oil-SF6 Transformer Bushing RIP/RIF Oil-Oil Transformer Bushing RIP/RIF High Current Transformer Bushing RIP/RIF GIS Outlet Bushing RIP/RIF Wall Bushing F",
    "operationTime": "at Hebei Project-Shandong Qixing High Voltage Electric Co",
    "description": "2016 Previous: 252kV Transformer Bushing in Operation at Sichuan Batang Substation (China State Grid Project) Next: 126kV Transformer Bushing in Operation at Hejing Yixin Photovoltaic Grid-Connected Power Station Let Us know Your Request  Shandong Qixing High Voltage Electric Co.",
    "images": [
      "1731894078716949488901574656",
      "1731894930716953063098699776",
      "1768468846870355185425739776",
      "1768524315870587839131742208",
      "1768533942870628218564575232",
      "1768533943870628220338733056",
      "1768811237871791276305608704",
      "1769394598874238072085098496"
    ]
  },
  {
    "file": "252kV-Transformer-Bushing-in-Operation-at-Sichuan-Batang-Substation--China-State-Grid-Project-.html",
    "title": "252kV Transformer Bushing in Operation at Sichuan Batang Substation (China State Grid Project)",
    "customer": "Shandong Dachi Electric Co",
    "project": ")-Shandong Qixing High Voltage Electric Co",
    "products": " RIP/RIF Oil-Air Transformer Bushing RIP/RIF Oil-SF6 Transformer Bushing RIP/RIF Oil-Oil Transformer Bushing RIP/RIF High Current Transformer Bushing RIP/RIF GIS Outlet Bushing RIP/RIF Wall Bushing F",
    "operationTime": "at Sichuan Batang Substation (China State Grid Project)-Shandong Qixing High Voltage Electric Co",
    "description": ", Ltd Project: Sichuan Batang Substation (State Grid Project) Products: 252kV Transformer Bushing Operation time: 11th Jun.",
    "images": [
      "1731894078716949488901574656",
      "1731894930716953063098699776",
      "1768468846870355185425739776",
      "1768524315870587839131742208",
      "1768533743870627380634910720",
      "1768533743870627384036454400",
      "1768533744870627386896969728",
      "1768811237871791276305608704",
      "1769394598874238072085098496"
    ]
  },
  {
    "file": "252kV-Transformer-Bushing-in-Operation-on-the-Chengdu-Chongqing-High-Speed-Railway.html",
    "title": "252kV Transformer Bushing in Operation on the Chengdu-Chongqing High-Speed Railway",
    "customer": "TBEA Xinjiang Transformer Group Co",
    "project": "Chengdu-Chongqing High-Speed Railway Products: 252kV Transformer Bushing Operation time: 28th Dec",
    "products": " RIP/RIF Oil-Air Transformer Bushing RIP/RIF Oil-SF6 Transformer Bushing RIP/RIF Oil-Oil Transformer Bushing RIP/RIF High Current Transformer Bushing RIP/RIF GIS Outlet Bushing RIP/RIF Wall Bushing F",
    "operationTime": "on the Chengdu-Chongqing High-Speed Railway-Shandong Qixing High Voltage Electric Co",
    "description": "2019 Previous: 126kV Transformer Bushing in Operation at Xinjiang Project Next: 220kV Transformer Bushing in Operation at Wuhai Power Supply Bureau's 220 Baoshan Substation Let Us know Your Request  Shandong Qixing High Voltage Electric Co.",
    "images": [
      "1731894078716949488901574656",
      "1731894930716953063098699776",
      "1768468846870355185425739776",
      "1768524315870587839131742208",
      "1768541952870661813320617984",
      "1768541952870661814998298624",
      "1768811237871791276305608704",
      "1769394598874238072085098496"
    ]
  },
  {
    "file": "330kV-GIS-Bushing-in-Operation-at-Shaanxi-Linyou-2-350MW-Low-Calorific-Value-Coal-Fired-Power-Plant.html",
    "title": "330kV GIS Bushing in Operation at Shaanxi Linyou 2×350MW Low-Calorific Value Coal-Fired Power Plant",
    "customer": "Xi'an XD Switchgear Electric CO",
    "project": "Shaanxi Linyou 2×350MW Low-Calorific Value Coal-Fired Power Plant Products: 330kV GIS Bushing Operation time: 1st Jan",
    "products": " RIP/RIF Oil-Air Transformer Bushing RIP/RIF Oil-SF6 Transformer Bushing RIP/RIF Oil-Oil Transformer Bushing RIP/RIF High Current Transformer Bushing RIP/RIF GIS Outlet Bushing RIP/RIF Wall Bushing F",
    "operationTime": "at Shaanxi Linyou 2×350MW Low-Calorific Value Coal-Fired Power Plant-Shandong Qixing High Voltage Electric Co",
    "description": ", Ltd Project: Shaanxi Linyou 2×350MW Low-Calorific Value Coal-Fired Power Plant Products: 330kV GIS Bushing Operation time: 1st Jan.",
    "images": [
      "1731894078716949488901574656",
      "1731894930716953063098699776",
      "1768468846870355185425739776",
      "1768524315870587839131742208",
      "1768541419870659578779996160",
      "1768541420870659580419969024",
      "1768541420870659582101884928",
      "1768541420870659583662166016",
      "1768541421870659585201475584",
      "1768541421870659586724007936",
      "1768541421870659588309454848",
      "1768811237871791276305608704",
      "1769394598874238072085098496"
    ]
  },
  {
    "file": "330kV-Transformer-Bushing-in-Operation-at-the-Energy-Storage-Power-Station-of-the-Gansu-Longyuan-Linze-Banqiao-Beitan-500MW-Photovoltaic-Desert-Control-Project-.html",
    "title": "330kV Transformer Bushing in Operation at the Energy Storage Power Station of the Gansu Longyuan Linze Banqiao Beitan 500MW Photovoltaic Desert Control Project.Shandong Qixing High Voltage Electric Co. Ltd",
    "customer": "Xi'an XD Transformer Co",
    "project": "Energy Storage Power Station of the Gansu Longyuan Linze Banqiao Beitan 500MW Photovoltaic Desert Control Project Products: 330kV Transformer Bushing Operation time: 20th Jan",
    "products": " RIP/RIF Oil-Air Transformer Bushing RIP/RIF Oil-SF6 Transformer Bushing RIP/RIF Oil-Oil Transformer Bushing RIP/RIF High Current Transformer Bushing RIP/RIF GIS Outlet Bushing RIP/RIF Wall Bushing F",
    "operationTime": "at the Energy Storage Power Station of the Gansu Longyuan Linze Banqiao Beitan 500MW Photovoltaic Desert Control Project",
    "description": "330kV Transformer Bushing in Operation at the Energy Storage Power Station of the Gansu Longyuan Linze Banqiao Beitan 500MW Photovoltaic Desert Control Project.",
    "images": [
      "1731894078716949488901574656",
      "1731894930716953063098699776",
      "1768468846870355185425739776",
      "1768524315870587839131742208",
      "1768534152870629096126218240",
      "1768534152870629098600820736",
      "1768811237871791276305608704",
      "1769394598874238072085098496"
    ]
  }
]